[
    {
        "name": "Autumn Heights",
        "chest_opened_img": "images/locations/puzzlepiece.png",
        "chest_unopened_img": "images/locations/puzzlepiece_desat.png",
        "children": [
            {
                "name": "[2-1] Windmill Hills",
                "access_rules": [
                    "2-1"
                ],
                "sections": [
                    {
                        "name": "Letter K",
                        "chest_opened_img": "images/locations/K.png",
                        "chest_unopened_img": "images/locations/K_desat.png"
                    },
                    {
                        "name": "Letter O",
                        "chest_opened_img": "images/locations/O.png",
                        "chest_unopened_img": "images/locations/O_desat.png"
                    },
                    {
                        "name": "Letter N",
                        "chest_opened_img": "images/locations/N.png",
                        "chest_unopened_img": "images/locations/N_desat.png"
                    },
                    {
                        "name": "Letter G",
                        "chest_opened_img": "images/locations/G.png",
                        "chest_unopened_img": "images/locations/G_desat.png"
                    },
                    {
                        "name": "Puzzle Pieces",
                        "item_count": 9
                    }
                ],
                "map_locations": [
                    {
                        "map": "autumnheights",
                        "x": 283,
                        "y": 456
                    }
                ]
            },
            {
                "name": "[2-2] Mountain Mania",
                "access_rules": [
                    "2-2"
                ],
                "sections": [
                    {
                        "name": "Letter K",
                        "chest_opened_img": "images/locations/K.png",
                        "chest_unopened_img": "images/locations/K_desat.png"
                    },
                    {
                        "name": "Letter O",
                        "chest_opened_img": "images/locations/O.png",
                        "chest_unopened_img": "images/locations/O_desat.png"
                    },
                    {
                        "name": "Letter N",
                        "chest_opened_img": "images/locations/N.png",
                        "chest_unopened_img": "images/locations/N_desat.png"
                    },
                    {
                        "name": "Letter G",
                        "chest_opened_img": "images/locations/G.png",
                        "chest_unopened_img": "images/locations/G_desat.png"
                    },
                    {
                        "name": "Puzzle Pieces",
                        "item_count": 6
                    },
                    {
                        "name": "Puzzle Piece - Dixie/Cranky"
                    }
                ],
                "map_locations": [
                    {
                        "map": "autumnheights",
                        "x": 404,
                        "y": 474
                    }
                ]
            },
            {
                "name": "[2-3] Horn Top Hop",
                "access_rules": [
                    "2-3"
                ],
                "sections": [
                    {
                        "name": "Letter K",
                        "chest_opened_img": "images/locations/K.png",
                        "chest_unopened_img": "images/locations/K_desat.png"
                    },
                    {
                        "name": "Letter O",
                        "chest_opened_img": "images/locations/O.png",
                        "chest_unopened_img": "images/locations/O_desat.png"
                    },
                    {
                        "name": "Letter N",
                        "chest_opened_img": "images/locations/N.png",
                        "chest_unopened_img": "images/locations/N_desat.png"
                    },
                    {
                        "name": "Letter G",
                        "chest_opened_img": "images/locations/G.png",
                        "chest_unopened_img": "images/locations/G_desat.png"
                    },
                    {
                        "name": "Puzzle Pieces",
                        "item_count": 5
                    }
                ],
                "map_locations": [
                    {
                        "map": "autumnheights",
                        "x": 506,
                        "y": 471
                    }
                ]
            },
            {
                "name": "[2-4] Sawmill Thrill",
                "access_rules": [
                    "2-4"
                ],
                "sections": [
                    {
                        "name": "Letter K",
                        "chest_opened_img": "images/locations/K.png",
                        "chest_unopened_img": "images/locations/K_desat.png"
                    },
                    {
                        "name": "Letter O",
                        "chest_opened_img": "images/locations/O.png",
                        "chest_unopened_img": "images/locations/O_desat.png"
                    },
                    {
                        "name": "Letter N",
                        "chest_opened_img": "images/locations/N.png",
                        "chest_unopened_img": "images/locations/N_desat.png"
                    },
                    {
                        "name": "Letter G",
                        "chest_opened_img": "images/locations/G.png",
                        "chest_unopened_img": "images/locations/G_desat.png"
                    },
                    {
                        "name": "Puzzle Pieces",
                        "item_count": 5
                    }
                ],
                "map_locations": [
                    {
                        "map": "autumnheights",
                        "x": 490,
                        "y": 390
                    }
                ]
            },
            {
                "name": "[2-A] Crumble Cavern",
                "access_rules": [
                    "2-A"
                ],
                "sections": [
                    {
                        "name": "Letter K",
                        "chest_opened_img": "images/locations/K.png",
                        "chest_unopened_img": "images/locations/K_desat.png"
                    },
                    {
                        "name": "Letter O",
                        "chest_opened_img": "images/locations/O.png",
                        "chest_unopened_img": "images/locations/O_desat.png"
                    },
                    {
                        "name": "Letter N",
                        "chest_opened_img": "images/locations/N.png",
                        "chest_unopened_img": "images/locations/N_desat.png"
                    },
                    {
                        "name": "Letter G",
                        "chest_opened_img": "images/locations/G.png",
                        "chest_unopened_img": "images/locations/G_desat.png"
                    },
                    {
                        "name": "Puzzle Pieces",
                        "item_count": 7
                    }
                ],
                "map_locations": [
                    {
                        "map": "autumnheights",
                        "x": 392,
                        "y": 380
                    }
                ]
            },
            {
                "name": "[2-B] Rodent Ruckus",
                "access_rules": [
                    "2-B"
                ],
                "sections": [
                    {
                        "name": "Letter K",
                        "chest_opened_img": "images/locations/K.png",
                        "chest_unopened_img": "images/locations/K_desat.png"
                    },
                    {
                        "name": "Letter O",
                        "chest_opened_img": "images/locations/O.png",
                        "chest_unopened_img": "images/locations/O_desat.png"
                    },
                    {
                        "name": "Letter N",
                        "chest_opened_img": "images/locations/N.png",
                        "chest_unopened_img": "images/locations/N_desat.png"
                    },
                    {
                        "name": "Letter G",
                        "chest_opened_img": "images/locations/G.png",
                        "chest_unopened_img": "images/locations/G_desat.png"
                    },
                    {
                        "name": "Puzzle Pieces",
                        "item_count": 5
                    }
                ],
                "map_locations": [
                    {
                        "map": "autumnheights",
                        "x": 308,
                        "y": 368
                    }
                ]
            },
            {
                "name": "[2-5] Alpine Incline",
                "access_rules": [
                    "2-5"
                ],
                "sections": [
                    {
                        "name": "Letter K",
                        "chest_opened_img": "images/locations/K.png",
                        "chest_unopened_img": "images/locations/K_desat.png"
                    },
                    {
                        "name": "Letter O",
                        "chest_opened_img": "images/locations/O.png",
                        "chest_unopened_img": "images/locations/O_desat.png"
                    },
                    {
                        "name": "Letter N",
                        "chest_opened_img": "images/locations/N.png",
                        "chest_unopened_img": "images/locations/N_desat.png"
                    },
                    {
                        "name": "Letter G",
                        "chest_opened_img": "images/locations/G.png",
                        "chest_unopened_img": "images/locations/G_desat.png"
                    },
                    {
                        "name": "Puzzle Pieces",
                        "item_count": 4
                    },
                    {
                        "name": "Puzzle Piece - Dixie"
                    }
                ],
                "map_locations": [
                    {
                        "map": "autumnheights",
                        "x": 443,
                        "y": 268
                    }
                ]
            },
            {
                "name": "[2-6] Wing Ding",
                "access_rules": [
                    "2-6"
                ],
                "sections": [
                    {
                        "name": "Letter K",
                        "chest_opened_img": "images/locations/K.png",
                        "chest_unopened_img": "images/locations/K_desat.png"
                    },
                    {
                        "name": "Letter O",
                        "chest_opened_img": "images/locations/O.png",
                        "chest_unopened_img": "images/locations/O_desat.png"
                    },
                    {
                        "name": "Letter N",
                        "chest_opened_img": "images/locations/N.png",
                        "chest_unopened_img": "images/locations/N_desat.png"
                    },
                    {
                        "name": "Letter G",
                        "chest_opened_img": "images/locations/G.png",
                        "chest_unopened_img": "images/locations/G_desat.png"
                    },
                    {
                        "name": "Puzzle Pieces",
                        "item_count": 4
                    },
                    {
                        "name": "Puzzle Piece - Dixie/Cranky"
                    }
                ],
                "map_locations": [
                    {
                        "map": "autumnheights",
                        "x": 372,
                        "y": 215
                    }
                ]
            },
            {
                "name": "[2-K] Bopopolis",
                "access_rules": [
                    "2-k"
                ],
                "sections": [
                    {
                        "name": "Puzzle Pieces",
                        "item_count": 5
                    }
                ],
                "map_locations": [
                    {
                        "map": "autumnheights",
                        "x": 405,
                        "y": 442
                    }
                ]
            },
            {
                "name": "[2-Boss] Mountaintop Tussle",
                "access_rules": [
                    "$CanReachBoss|2"
                ],
                "sections": [
                    {
                        "name": "Defeat Skowl, The Startling",
                        "chest_opened_img": "images/locations/Skowl.png",
                        "chest_unopened_img": "images/locations/Skowl_desat.png"
                    }
                ],
                "map_locations": [
                    {
                        "map": "autumnheights",
                        "x": 445,
                        "y": 190
                    }
                ]
            }
        ]
    }
]